nutikacompile/README.MD
nutikacompile/__init__.py
nutikacompile/requirements.txt
nutikacompile/thirdparty.json
nutikacompile-0.13.dist-info/LICENSE.rst
nutikacompile-0.13.dist-info/METADATA
nutikacompile-0.13.dist-info/WHEEL
nutikacompile-0.13.dist-info/top_level.txt
nutikacompile-0.13.dist-info/RECORD
