Metadata-Version: 2.1
Name: nutikacompile
Version: 0.13
Summary: A function that creates the cmd line for nuitka and executes it - Windows only
Home-page: https://github.com/hansalemaos/nutikacompile
Author: Johannes Fischer
Author-email: aulasparticularesdealemaosp@gmail.com
License: MIT
Keywords: nuitka,exe,compile
Classifier: Development Status :: 4 - Beta
Classifier: Programming Language :: Python :: 3 :: Only
Classifier: Programming Language :: Python :: 3.10
Classifier: Topic :: Software Development :: Libraries :: Python Modules
Classifier: Topic :: Utilities
License-File: LICENSE.rst
Requires-Dist: FastCopyFast
Requires-Dist: Pillow
Requires-Dist: touchtouch
